{
  "name": "pfit4ls",
  "number": 2601,
  "classification": "SUR2-AN",
  "N": 3,
  "M": 0,
  "Nnl": 3,
  "Mnl": 0,
  "Nz": 3,
  "Fbest_raw": "0.0000000",
  "Fbest": 0.0,
  "feasible": true,
  "in_uno_429_subset": true,
  "mod_file_available": true,
  "gms_file_available": true,
  "dag_file_available": true,
  "res_file_available": true,
  "other_files": [],
  "files": {
    "dag": {
      "filename": "pfit4ls.dag",
      "url": "https://arnold-neumaier.at/glopt/coconut/Benchmark/Library2/pfit4ls.dag",
      "bytes": 1498
    },
    "gms": {
      "filename": "pfit4ls.gms",
      "url": "https://arnold-neumaier.at/glopt/coconut/Benchmark/Library2/pfit4ls.gms",
      "bytes": 823
    },
    "mod": {
      "filename": "pfit4ls.mod",
      "url": "https://arnold-neumaier.at/glopt/coconut/Benchmark/Library2/pfit4ls.mod",
      "bytes": 770
    },
    "res": {
      "filename": "pfit4ls.res",
      "url": "https://arnold-neumaier.at/glopt/coconut/Benchmark/Library2/RES/pfit4ls.res",
      "bytes": 166
    },
    "nl": {
      "filename": "pfit4ls.nl",
      "bytes": 883
    }
  },
  "detail_page": "https://arnold-neumaier.at/glopt/coconut/Benchmark/Library2/pfit4ls.htm",
  "source_index": "https://arnold-neumaier.at/glopt/coconut/Benchmark/Library2_new_v1.html",
  "_all_available_downloaded": true,
  "nl_file_available": true,
  "nl_conversion": {
    "status": "converted",
    "reason": ""
  }
}